py-executor/__init__.py
py-executor/bootstrap.py
py-executor/executor.py
py-executor/helper.py
py-executor/main.py
py-executor/start.py
starfall/__init__.py
starfall/executor.py
starfall/helper.py
starfall/main.py
starfall/setting.py
starfall/start.py
starfall-0.0.7.dist-info/LICENSE
starfall-0.0.7.dist-info/METADATA
starfall-0.0.7.dist-info/WHEEL
starfall-0.0.7.dist-info/top_level.txt
starfall-0.0.7.dist-info/RECORD
