Metadata-Version: 2.1
Name: starfall
Version: 0.0.7
Summary: An executor of Cron Job
Home-page: https://github.com/parselife/starfall/tree/master/
Author: Alex
Author-email: yxfacw@163.com
License: MIT License
Keywords: Cron Job Executor
Classifier: Development Status :: 4 - Beta
Classifier: Intended Audience :: Developers
Classifier: License :: OSI Approved :: MIT License
Classifier: Natural Language :: English
Classifier: Programming Language :: Python :: 3.6
Classifier: Programming Language :: Python :: 3.7
Classifier: Programming Language :: Python :: 3.8
Classifier: Programming Language :: Python :: 3.9
Classifier: Programming Language :: Python :: 3.10
Requires-Python: >=3.6
License-File: LICENSE
Requires-Dist: waitress
Requires-Dist: Flask
Requires-Dist: Werkzeug
Requires-Dist: Requests
